breakword/__init__.py
breakword/common_words.py
breakword-0.3.2.dist-info/METADATA
breakword-0.3.2.dist-info/WHEEL
breakword-0.3.2.dist-info/licenses/LICENSE
breakword-0.3.2.dist-info/RECORD
