Metadata-Version: 2.3
Name: breakword
Version: 0.3.2
Summary: Mixing breakpoints with print debugging.
Project-URL: Repository, https://github.com/breuleux/breakword
Project-URL: Homepage, https://github.com/breuleux/breakword
Author-email: Olivier Breuleux <breuleux@gmail.com>
License-Expression: MIT
License-File: LICENSE
Keywords: breakpoint,debug,print
Classifier: Development Status :: 4 - Beta
Classifier: Intended Audience :: Developers
Classifier: Topic :: Software Development :: Build Tools
Classifier: Topic :: Software Development :: Debuggers
Requires-Python: >=3.7
